litlm.py
litlm-0.2.0.dist-info/METADATA
litlm-0.2.0.dist-info/WHEEL
litlm-0.2.0.dist-info/top_level.txt
litlm-0.2.0.dist-info/RECORD
