Metadata-Version: 2.4
Name: litlm
Version: 0.2.0
Summary: Minimalist litellm wrapper for simpler requests and better openrouter support
Home-page: https://github.com/sileod/litlm
Author: Damien Sileo
Classifier: License :: OSI Approved :: MIT License
Classifier: Programming Language :: Python
Classifier: Operating System :: OS Independent
Requires-Python: >=3.6
Requires-Dist: litellm
Requires-Dist: tqdm
Requires-Dist: requests
Requires-Dist: appdirs
Requires-Dist: nest_asyncio
Dynamic: author
Dynamic: classifier
Dynamic: description
Dynamic: description-content-type
Dynamic: home-page
Dynamic: requires-dist
Dynamic: requires-python
Dynamic: summary
